{
  "$schema": "https://developer.microsoft.com/json-schemas/fabric/item/report/definition/visualContainer/2.9.0/schema.json",
  "name": "27ab2cf77ccb34fb8040",
  "position": {
    "x": 20,
    "y": 150,
    "z": 2000,
    "height": 250,
    "width": 610,
    "tabOrder": 2000
  },
  "visual": {
    "visualType": "lineChart",
    "query": {
      "queryState": {
        "Category": {
          "projections": [
            {
              "field": {
                "Column": {
                  "Expression": {
                    "SourceRef": {
                      "Entity": "Monthly Performance"
                    }
                  },
                  "Property": "Order Month"
                }
              },
              "queryRef": "Monthly Performance.Order Month",
              "nativeQueryRef": "Order Month",
              "active": true
            }
          ]
        },
        "Y": {
          "projections": [
            {
              "field": {
                "Aggregation": {
                  "Expression": {
                    "Column": {
                      "Expression": {
                        "SourceRef": {
                          "Entity": "Monthly Performance"
                        }
                      },
                      "Property": "Completed Revenue"
                    }
                  },
                  "Function": 0
                }
              },
              "queryRef": "Sum(Monthly Performance.Completed Revenue)",
              "nativeQueryRef": "Sum of Completed Revenue"
            }
          ]
        }
      }
    },
    "objects": {
      "legend": [
        {
          "properties": {
            "show": {
              "expr": {
                "Literal": {
                  "Value": "false"
                }
              }
            }
          }
        }
      ],
      "dataPoint": [
        {
          "properties": {
            "defaultColor": {
              "solid": {
                "color": {
                  "expr": {
                    "Literal": {
                      "Value": "'#13B5A4'"
                    }
                  }
                }
              }
            }
          }
        }
      ],
      "valueAxis": [
        {
          "properties": {
            "gridlineStyle": {
              "expr": {
                "Literal": {
                  "Value": "'dotted'"
                }
              }
            }
          }
        }
      ]
    },
    "visualContainerObjects": {
      "title": [
        {
          "properties": {
            "show": {
              "expr": {
                "Literal": {
                  "Value": "true"
                }
              }
            },
            "text": {
              "expr": {
                "Literal": {
                  "Value": "'Monthly completed revenue'"
                }
              }
            },
            "fontSize": {
              "expr": {
                "Literal": {
                  "Value": "14D"
                }
              }
            },
            "bold": {
              "expr": {
                "Literal": {
                  "Value": "true"
                }
              }
            },
            "fontColor": {
              "solid": {
                "color": {
                  "expr": {
                    "Literal": {
                      "Value": "'#172033'"
                    }
                  }
                }
              }
            }
          }
        }
      ],
      "background": [
        {
          "properties": {
            "show": {
              "expr": {
                "Literal": {
                  "Value": "true"
                }
              }
            },
            "color": {
              "solid": {
                "color": {
                  "expr": {
                    "Literal": {
                      "Value": "'#FFFFFF'"
                    }
                  }
                }
              }
            },
            "transparency": {
              "expr": {
                "Literal": {
                  "Value": "0D"
                }
              }
            }
          }
        }
      ],
      "border": [
        {
          "properties": {
            "show": {
              "expr": {
                "Literal": {
                  "Value": "true"
                }
              }
            },
            "color": {
              "solid": {
                "color": {
                  "expr": {
                    "Literal": {
                      "Value": "'#DCE3EC'"
                    }
                  }
                }
              }
            },
            "radius": {
              "expr": {
                "Literal": {
                  "Value": "8D"
                }
              }
            }
          }
        }
      ]
    }
  }
}
